fastapi_task_worker/__init__.py
fastapi_task_worker/base.py
fastapi_task_worker/constant.py
fastapi_task_worker/event.py
fastapi_task_worker/py.typed
fastapi_task_worker/rabbit.py
fastapi_task_worker/task.py
fastapi_task_worker/task_worker.py
fastapi_task_worker-0.1.0.dist-info/METADATA
fastapi_task_worker-0.1.0.dist-info/WHEEL
fastapi_task_worker-0.1.0.dist-info/RECORD
