Metadata-Version: 2.4
Name: fastapi-task-worker
Version: 0.1.0
Summary: Fastapi Task Worker
Requires-Python: >=3.12
Requires-Dist: aio-pika>=9.5.5
Requires-Dist: fastapi>=0.115.12
Requires-Dist: pydantic>=2.11.4
